<population>
	<param weightGoodNumbers="32745" weightPortThreeOne="45113" weightPortTwoOne="79086" weightMissingMaterial="25803" weightEdgeGeneral="10084" weightWood="60374" weightBrick="65541" weightGrain="69150" weightSheep="58924" weightStone="83167" weightRoadGeneral="1971" weightLongestRoad="65334" weightExtensionRoad="2489" weightSpaceForVillage="41632" weightThiefMoveBase="94176" weightThiefMoveOtherBuilding="84667" weightThiefMoveMyBuilding="3525" weightThiefMoveProb="5366" weightVillageGeneral="99812" weightVillageGoodNumbers="80503" weightVillagePortThreeOne="24393" weightVillagePortTwoOne="14507" weightTownGeneral="68951" weightTownGoodNumbers="3342" weightBuyActionCardGeneral="43240" weightUseActionCardGeneral="2891" weightUseMatFromPlGeneral="94292" weightUseTwoMatRoadGeneral="59768" weightUseTwoMatVillageGeneral="88983" weightUseTwoMatTownGeneral="27748" weightUseTwoMatActGeneral="25282" weightUseTwoRoadGeneral="49238">
		<fitness>51</fitness>
	</param>
	<param weightGoodNumbers="34433" weightPortThreeOne="12099" weightPortTwoOne="79086" weightMissingMaterial="37929" weightEdgeGeneral="10084" weightWood="60374" weightBrick="65541" weightGrain="69150" weightSheep="58924" weightStone="83167" weightRoadGeneral="1971" weightLongestRoad="65334" weightExtensionRoad="30265" weightSpaceForVillage="41632" weightThiefMoveBase="13282" weightThiefMoveOtherBuilding="84667" weightThiefMoveMyBuilding="3525" weightThiefMoveProb="5366" weightVillageGeneral="77849" weightVillageGoodNumbers="80503" weightVillagePortThreeOne="24393" weightVillagePortTwoOne="14507" weightTownGeneral="68951" weightTownGoodNumbers="3342" weightBuyActionCardGeneral="43240" weightUseActionCardGeneral="2891" weightUseMatFromPlGeneral="94292" weightUseTwoMatRoadGeneral="64157" weightUseTwoMatVillageGeneral="52253" weightUseTwoMatTownGeneral="79812" weightUseTwoMatActGeneral="25282" weightUseTwoRoadGeneral="69481">
		<fitness>44</fitness>
	</param>
	<param weightGoodNumbers="34433" weightPortThreeOne="12099" weightPortTwoOne="79086" weightMissingMaterial="37929" weightEdgeGeneral="10084" weightWood="60374" weightBrick="65541" weightGrain="69150" weightSheep="58924" weightStone="83167" weightRoadGeneral="1971" weightLongestRoad="65334" weightExtensionRoad="30265" weightSpaceForVillage="41632" weightThiefMoveBase="13282" weightThiefMoveOtherBuilding="84667" weightThiefMoveMyBuilding="3525" weightThiefMoveProb="5366" weightVillageGeneral="77849" weightVillageGoodNumbers="80503" weightVillagePortThreeOne="24393" weightVillagePortTwoOne="14507" weightTownGeneral="68951" weightTownGoodNumbers="3342" weightBuyActionCardGeneral="48433" weightUseActionCardGeneral="2891" weightUseMatFromPlGeneral="94292" weightUseTwoMatRoadGeneral="59768" weightUseTwoMatVillageGeneral="88983" weightUseTwoMatTownGeneral="27748" weightUseTwoMatActGeneral="25282" weightUseTwoRoadGeneral="49238">
		<fitness>61</fitness>
	</param>
	<param weightGoodNumbers="32745" weightPortThreeOne="12099" weightPortTwoOne="79086" weightMissingMaterial="37929" weightEdgeGeneral="10084" weightWood="60374" weightBrick="65541" weightGrain="69150" weightSheep="58924" weightStone="83167" weightRoadGeneral="1971" weightLongestRoad="65334" weightExtensionRoad="30265" weightSpaceForVillage="41632" weightThiefMoveBase="13282" weightThiefMoveOtherBuilding="84667" weightThiefMoveMyBuilding="3525" weightThiefMoveProb="5366" weightVillageGeneral="77849" weightVillageGoodNumbers="80503" weightVillagePortThreeOne="24393" weightVillagePortTwoOne="14507" weightTownGeneral="68951" weightTownGoodNumbers="3342" weightBuyActionCardGeneral="43240" weightUseActionCardGeneral="2891" weightUseMatFromPlGeneral="94292" weightUseTwoMatRoadGeneral="59768" weightUseTwoMatVillageGeneral="88983" weightUseTwoMatTownGeneral="27748" weightUseTwoMatActGeneral="25282" weightUseTwoRoadGeneral="49238">
		<fitness>52</fitness>
	</param>
	<param weightGoodNumbers="32745" weightPortThreeOne="45113" weightPortTwoOne="79086" weightMissingMaterial="25803" weightEdgeGeneral="10084" weightWood="60374" weightBrick="65541" weightGrain="69150" weightSheep="58924" weightStone="83167" weightRoadGeneral="1971" weightLongestRoad="65334" weightExtensionRoad="2489" weightSpaceForVillage="41632" weightThiefMoveBase="94176" weightThiefMoveOtherBuilding="84667" weightThiefMoveMyBuilding="3525" weightThiefMoveProb="5366" weightVillageGeneral="99812" weightVillageGoodNumbers="80503" weightVillagePortThreeOne="24393" weightVillagePortTwoOne="14507" weightTownGeneral="68951" weightTownGoodNumbers="3342" weightBuyActionCardGeneral="43240" weightUseActionCardGeneral="2891" weightUseMatFromPlGeneral="94292" weightUseTwoMatRoadGeneral="59768" weightUseTwoMatVillageGeneral="88983" weightUseTwoMatTownGeneral="27748" weightUseTwoMatActGeneral="25282" weightUseTwoRoadGeneral="49238">
		<fitness>49</fitness>
	</param>
	<param weightGoodNumbers="32745" weightPortThreeOne="45113" weightPortTwoOne="79086" weightMissingMaterial="37929" weightEdgeGeneral="10084" weightWood="60374" weightBrick="65541" weightGrain="69150" weightSheep="58924" weightStone="83167" weightRoadGeneral="1971" weightLongestRoad="65334" weightExtensionRoad="2489" weightSpaceForVillage="41632" weightThiefMoveBase="94176" weightThiefMoveOtherBuilding="84667" weightThiefMoveMyBuilding="3525" weightThiefMoveProb="5366" weightVillageGeneral="99812" weightVillageGoodNumbers="80503" weightVillagePortThreeOne="24393" weightVillagePortTwoOne="14507" weightTownGeneral="68951" weightTownGoodNumbers="3342" weightBuyActionCardGeneral="43240" weightUseActionCardGeneral="2891" weightUseMatFromPlGeneral="94292" weightUseTwoMatRoadGeneral="64157" weightUseTwoMatVillageGeneral="52253" weightUseTwoMatTownGeneral="79812" weightUseTwoMatActGeneral="25282" weightUseTwoRoadGeneral="79684">
		<fitness>55</fitness>
	</param>
	<param weightGoodNumbers="32745" weightPortThreeOne="12099" weightPortTwoOne="79086" weightMissingMaterial="37929" weightEdgeGeneral="10084" weightWood="60374" weightBrick="65541" weightGrain="69150" weightSheep="58924" weightStone="83167" weightRoadGeneral="1971" weightLongestRoad="65334" weightExtensionRoad="30265" weightSpaceForVillage="41632" weightThiefMoveBase="13282" weightThiefMoveOtherBuilding="84667" weightThiefMoveMyBuilding="3525" weightThiefMoveProb="5366" weightVillageGeneral="77849" weightVillageGoodNumbers="80503" weightVillagePortThreeOne="24393" weightVillagePortTwoOne="14507" weightTownGeneral="68951" weightTownGoodNumbers="3342" weightBuyActionCardGeneral="48433" weightUseActionCardGeneral="2891" weightUseMatFromPlGeneral="94292" weightUseTwoMatRoadGeneral="64157" weightUseTwoMatVillageGeneral="52253" weightUseTwoMatTownGeneral="79812" weightUseTwoMatActGeneral="25282" weightUseTwoRoadGeneral="69481">
		<fitness>54</fitness>
	</param>
	<param weightGoodNumbers="34433" weightPortThreeOne="45113" weightPortTwoOne="79086" weightMissingMaterial="37929" weightEdgeGeneral="10084" weightWood="60374" weightBrick="65541" weightGrain="69150" weightSheep="58924" weightStone="83167" weightRoadGeneral="1971" weightLongestRoad="89704" weightExtensionRoad="2489" weightSpaceForVillage="41632" weightThiefMoveBase="94176" weightThiefMoveOtherBuilding="84667" weightThiefMoveMyBuilding="3525" weightThiefMoveProb="5366" weightVillageGeneral="99812" weightVillageGoodNumbers="64653" weightVillagePortThreeOne="94116" weightVillagePortTwoOne="14507" weightTownGeneral="68951" weightTownGoodNumbers="3342" weightBuyActionCardGeneral="43240" weightUseActionCardGeneral="2891" weightUseMatFromPlGeneral="94292" weightUseTwoMatRoadGeneral="59768" weightUseTwoMatVillageGeneral="88983" weightUseTwoMatTownGeneral="27748" weightUseTwoMatActGeneral="25282" weightUseTwoRoadGeneral="49238">
		<fitness>48</fitness>
	</param>
	<param weightGoodNumbers="32745" weightPortThreeOne="45113" weightPortTwoOne="79086" weightMissingMaterial="37929" weightEdgeGeneral="46977" weightWood="80142" weightBrick="65541" weightGrain="69150" weightSheep="58924" weightStone="83167" weightRoadGeneral="1971" weightLongestRoad="65334" weightExtensionRoad="2489" weightSpaceForVillage="41632" weightThiefMoveBase="94176" weightThiefMoveOtherBuilding="84667" weightThiefMoveMyBuilding="3525" weightThiefMoveProb="5366" weightVillageGeneral="99812" weightVillageGoodNumbers="80503" weightVillagePortThreeOne="24393" weightVillagePortTwoOne="14507" weightTownGeneral="68951" weightTownGoodNumbers="3342" weightBuyActionCardGeneral="48433" weightUseActionCardGeneral="2891" weightUseMatFromPlGeneral="94292" weightUseTwoMatRoadGeneral="59768" weightUseTwoMatVillageGeneral="88983" weightUseTwoMatTownGeneral="27748" weightUseTwoMatActGeneral="25282" weightUseTwoRoadGeneral="49238">
		<fitness>51</fitness>
	</param>
	<param weightGoodNumbers="32745" weightPortThreeOne="45113" weightPortTwoOne="79086" weightMissingMaterial="25803" weightEdgeGeneral="46977" weightWood="80142" weightBrick="65541" weightGrain="69150" weightSheep="58924" weightStone="83167" weightRoadGeneral="1971" weightLongestRoad="65334" weightExtensionRoad="2489" weightSpaceForVillage="41632" weightThiefMoveBase="48082" weightThiefMoveOtherBuilding="84667" weightThiefMoveMyBuilding="27155" weightThiefMoveProb="5366" weightVillageGeneral="99812" weightVillageGoodNumbers="80503" weightVillagePortThreeOne="24393" weightVillagePortTwoOne="14507" weightTownGeneral="68951" weightTownGoodNumbers="3342" weightBuyActionCardGeneral="43240" weightUseActionCardGeneral="2891" weightUseMatFromPlGeneral="94292" weightUseTwoMatRoadGeneral="64157" weightUseTwoMatVillageGeneral="52253" weightUseTwoMatTownGeneral="79812" weightUseTwoMatActGeneral="90138" weightUseTwoRoadGeneral="49238">
		<fitness>50</fitness>
	</param>
	<param weightGoodNumbers="32745" weightPortThreeOne="45113" weightPortTwoOne="79086" weightMissingMaterial="37929" weightEdgeGeneral="10084" weightWood="60374" weightBrick="65541" weightGrain="69150" weightSheep="58924" weightStone="83167" weightRoadGeneral="1971" weightLongestRoad="65334" weightExtensionRoad="2489" weightSpaceForVillage="41632" weightThiefMoveBase="94176" weightThiefMoveOtherBuilding="84667" weightThiefMoveMyBuilding="3525" weightThiefMoveProb="5366" weightVillageGeneral="99812" weightVillageGoodNumbers="80503" weightVillagePortThreeOne="24393" weightVillagePortTwoOne="14507" weightTownGeneral="68951" weightTownGoodNumbers="3342" weightBuyActionCardGeneral="43240" weightUseActionCardGeneral="2891" weightUseMatFromPlGeneral="94292" weightUseTwoMatRoadGeneral="64157" weightUseTwoMatVillageGeneral="52253" weightUseTwoMatTownGeneral="79812" weightUseTwoMatActGeneral="25282" weightUseTwoRoadGeneral="79684">
		<fitness>58</fitness>
	</param>
	<param weightGoodNumbers="32745" weightPortThreeOne="71007" weightPortTwoOne="5923" weightMissingMaterial="25803" weightEdgeGeneral="10084" weightWood="60374" weightBrick="65541" weightGrain="69150" weightSheep="58924" weightStone="83167" weightRoadGeneral="1971" weightLongestRoad="65334" weightExtensionRoad="2489" weightSpaceForVillage="41632" weightThiefMoveBase="94176" weightThiefMoveOtherBuilding="84667" weightThiefMoveMyBuilding="3525" weightThiefMoveProb="5366" weightVillageGeneral="99812" weightVillageGoodNumbers="80503" weightVillagePortThreeOne="24393" weightVillagePortTwoOne="14507" weightTownGeneral="68951" weightTownGoodNumbers="3342" weightBuyActionCardGeneral="43240" weightUseActionCardGeneral="2891" weightUseMatFromPlGeneral="94292" weightUseTwoMatRoadGeneral="59768" weightUseTwoMatVillageGeneral="88983" weightUseTwoMatTownGeneral="27748" weightUseTwoMatActGeneral="25282" weightUseTwoRoadGeneral="49238">
		<fitness>55</fitness>
	</param>
	<param weightGoodNumbers="32745" weightPortThreeOne="45113" weightPortTwoOne="79086" weightMissingMaterial="25803" weightEdgeGeneral="10084" weightWood="60374" weightBrick="65541" weightGrain="69150" weightSheep="58924" weightStone="83167" weightRoadGeneral="1971" weightLongestRoad="65334" weightExtensionRoad="2489" weightSpaceForVillage="41632" weightThiefMoveBase="94176" weightThiefMoveOtherBuilding="84667" weightThiefMoveMyBuilding="3525" weightThiefMoveProb="5366" weightVillageGeneral="99812" weightVillageGoodNumbers="80503" weightVillagePortThreeOne="24393" weightVillagePortTwoOne="14507" weightTownGeneral="68951" weightTownGoodNumbers="3342" weightBuyActionCardGeneral="43240" weightUseActionCardGeneral="2891" weightUseMatFromPlGeneral="94292" weightUseTwoMatRoadGeneral="64157" weightUseTwoMatVillageGeneral="52253" weightUseTwoMatTownGeneral="79812" weightUseTwoMatActGeneral="25282" weightUseTwoRoadGeneral="79684">
		<fitness>55</fitness>
	</param>
	<param weightGoodNumbers="32745" weightPortThreeOne="45113" weightPortTwoOne="79086" weightMissingMaterial="25803" weightEdgeGeneral="10084" weightWood="60374" weightBrick="65541" weightGrain="69150" weightSheep="58924" weightStone="83167" weightRoadGeneral="1971" weightLongestRoad="65334" weightExtensionRoad="2489" weightSpaceForVillage="41632" weightThiefMoveBase="94176" weightThiefMoveOtherBuilding="84667" weightThiefMoveMyBuilding="3525" weightThiefMoveProb="5366" weightVillageGeneral="99812" weightVillageGoodNumbers="80503" weightVillagePortThreeOne="24393" weightVillagePortTwoOne="14507" weightTownGeneral="68951" weightTownGoodNumbers="3342" weightBuyActionCardGeneral="43240" weightUseActionCardGeneral="2891" weightUseMatFromPlGeneral="94292" weightUseTwoMatRoadGeneral="64157" weightUseTwoMatVillageGeneral="52253" weightUseTwoMatTownGeneral="79812" weightUseTwoMatActGeneral="44470" weightUseTwoRoadGeneral="56679">
		<fitness>66</fitness>
	</param>
	<param weightGoodNumbers="34433" weightPortThreeOne="45113" weightPortTwoOne="79086" weightMissingMaterial="37929" weightEdgeGeneral="10084" weightWood="60374" weightBrick="65541" weightGrain="69150" weightSheep="58924" weightStone="83167" weightRoadGeneral="1971" weightLongestRoad="65334" weightExtensionRoad="2489" weightSpaceForVillage="41632" weightThiefMoveBase="94176" weightThiefMoveOtherBuilding="84667" weightThiefMoveMyBuilding="3525" weightThiefMoveProb="5366" weightVillageGeneral="99812" weightVillageGoodNumbers="80503" weightVillagePortThreeOne="24393" weightVillagePortTwoOne="14507" weightTownGeneral="68951" weightTownGoodNumbers="3342" weightBuyActionCardGeneral="43240" weightUseActionCardGeneral="2891" weightUseMatFromPlGeneral="94292" weightUseTwoMatRoadGeneral="64157" weightUseTwoMatVillageGeneral="52253" weightUseTwoMatTownGeneral="79812" weightUseTwoMatActGeneral="44470" weightUseTwoRoadGeneral="56679">
		<fitness>61</fitness>
	</param>
	<param weightGoodNumbers="32745" weightPortThreeOne="45113" weightPortTwoOne="79086" weightMissingMaterial="25803" weightEdgeGeneral="10084" weightWood="60374" weightBrick="65541" weightGrain="69150" weightSheep="58924" weightStone="83167" weightRoadGeneral="1971" weightLongestRoad="89704" weightExtensionRoad="2489" weightSpaceForVillage="41632" weightThiefMoveBase="94176" weightThiefMoveOtherBuilding="84667" weightThiefMoveMyBuilding="3525" weightThiefMoveProb="5366" weightVillageGeneral="99812" weightVillageGoodNumbers="64653" weightVillagePortThreeOne="94116" weightVillagePortTwoOne="14507" weightTownGeneral="68951" weightTownGoodNumbers="3342" weightBuyActionCardGeneral="43240" weightUseActionCardGeneral="2891" weightUseMatFromPlGeneral="94292" weightUseTwoMatRoadGeneral="64157" weightUseTwoMatVillageGeneral="52253" weightUseTwoMatTownGeneral="79812" weightUseTwoMatActGeneral="25282" weightUseTwoRoadGeneral="69481">
		<fitness>57</fitness>
	</param>
	<param weightGoodNumbers="32745" weightPortThreeOne="45113" weightPortTwoOne="79086" weightMissingMaterial="25803" weightEdgeGeneral="10084" weightWood="60374" weightBrick="65541" weightGrain="69150" weightSheep="58924" weightStone="83167" weightRoadGeneral="1971" weightLongestRoad="65334" weightExtensionRoad="2489" weightSpaceForVillage="41632" weightThiefMoveBase="94176" weightThiefMoveOtherBuilding="84667" weightThiefMoveMyBuilding="3525" weightThiefMoveProb="5366" weightVillageGeneral="99812" weightVillageGoodNumbers="80503" weightVillagePortThreeOne="24393" weightVillagePortTwoOne="14507" weightTownGeneral="68951" weightTownGoodNumbers="3342" weightBuyActionCardGeneral="43240" weightUseActionCardGeneral="2891" weightUseMatFromPlGeneral="94292" weightUseTwoMatRoadGeneral="64157" weightUseTwoMatVillageGeneral="52253" weightUseTwoMatTownGeneral="79812" weightUseTwoMatActGeneral="25282" weightUseTwoRoadGeneral="79684">
		<fitness>59</fitness>
	</param>
	<param weightGoodNumbers="32745" weightPortThreeOne="12099" weightPortTwoOne="79086" weightMissingMaterial="37929" weightEdgeGeneral="46977" weightWood="80142" weightBrick="65541" weightGrain="69150" weightSheep="58924" weightStone="83167" weightRoadGeneral="1971" weightLongestRoad="65334" weightExtensionRoad="2489" weightSpaceForVillage="41632" weightThiefMoveBase="94176" weightThiefMoveOtherBuilding="84667" weightThiefMoveMyBuilding="3525" weightThiefMoveProb="66576" weightVillageGeneral="99812" weightVillageGoodNumbers="80503" weightVillagePortThreeOne="24393" weightVillagePortTwoOne="14507" weightTownGeneral="68951" weightTownGoodNumbers="3342" weightBuyActionCardGeneral="43240" weightUseActionCardGeneral="2891" weightUseMatFromPlGeneral="94292" weightUseTwoMatRoadGeneral="64157" weightUseTwoMatVillageGeneral="52253" weightUseTwoMatTownGeneral="79812" weightUseTwoMatActGeneral="44470" weightUseTwoRoadGeneral="56679">
		<fitness>49</fitness>
	</param>
	<param weightGoodNumbers="32745" weightPortThreeOne="45113" weightPortTwoOne="79086" weightMissingMaterial="25803" weightEdgeGeneral="46977" weightWood="80142" weightBrick="65541" weightGrain="69150" weightSheep="58924" weightStone="83167" weightRoadGeneral="1971" weightLongestRoad="65334" weightExtensionRoad="2489" weightSpaceForVillage="41632" weightThiefMoveBase="48082" weightThiefMoveOtherBuilding="84667" weightThiefMoveMyBuilding="3525" weightThiefMoveProb="5366" weightVillageGeneral="99812" weightVillageGoodNumbers="80503" weightVillagePortThreeOne="24393" weightVillagePortTwoOne="14507" weightTownGeneral="68951" weightTownGoodNumbers="3342" weightBuyActionCardGeneral="43240" weightUseActionCardGeneral="2891" weightUseMatFromPlGeneral="94292" weightUseTwoMatRoadGeneral="64157" weightUseTwoMatVillageGeneral="52253" weightUseTwoMatTownGeneral="79812" weightUseTwoMatActGeneral="44470" weightUseTwoRoadGeneral="56679">
		<fitness>46</fitness>
	</param>
	<param weightGoodNumbers="32745" weightPortThreeOne="12099" weightPortTwoOne="79086" weightMissingMaterial="25803" weightEdgeGeneral="10084" weightWood="60374" weightBrick="65541" weightGrain="69150" weightSheep="58924" weightStone="83167" weightRoadGeneral="1971" weightLongestRoad="65334" weightExtensionRoad="2489" weightSpaceForVillage="41632" weightThiefMoveBase="94176" weightThiefMoveOtherBuilding="84667" weightThiefMoveMyBuilding="27155" weightThiefMoveProb="5366" weightVillageGeneral="99812" weightVillageGoodNumbers="80503" weightVillagePortThreeOne="24393" weightVillagePortTwoOne="14507" weightTownGeneral="68951" weightTownGoodNumbers="3342" weightBuyActionCardGeneral="48433" weightUseActionCardGeneral="2891" weightUseMatFromPlGeneral="94292" weightUseTwoMatRoadGeneral="59768" weightUseTwoMatVillageGeneral="88983" weightUseTwoMatTownGeneral="27748" weightUseTwoMatActGeneral="25282" weightUseTwoRoadGeneral="49238">
		<fitness>57</fitness>
	</param>
	<param weightGoodNumbers="32745" weightPortThreeOne="12099" weightPortTwoOne="79086" weightMissingMaterial="25803" weightEdgeGeneral="10084" weightWood="60374" weightBrick="65541" weightGrain="69150" weightSheep="58924" weightStone="83167" weightRoadGeneral="1971" weightLongestRoad="65334" weightExtensionRoad="2489" weightSpaceForVillage="41632" weightThiefMoveBase="94176" weightThiefMoveOtherBuilding="84667" weightThiefMoveMyBuilding="3525" weightThiefMoveProb="5366" weightVillageGeneral="99812" weightVillageGoodNumbers="80503" weightVillagePortThreeOne="24393" weightVillagePortTwoOne="14507" weightTownGeneral="68951" weightTownGoodNumbers="3342" weightBuyActionCardGeneral="43240" weightUseActionCardGeneral="2891" weightUseMatFromPlGeneral="94292" weightUseTwoMatRoadGeneral="64157" weightUseTwoMatVillageGeneral="52253" weightUseTwoMatTownGeneral="79812" weightUseTwoMatActGeneral="44470" weightUseTwoRoadGeneral="56679">
		<fitness>56</fitness>
	</param>
	<param weightGoodNumbers="32745" weightPortThreeOne="45113" weightPortTwoOne="79086" weightMissingMaterial="25803" weightEdgeGeneral="10084" weightWood="60374" weightBrick="65541" weightGrain="69150" weightSheep="58924" weightStone="83167" weightRoadGeneral="1971" weightLongestRoad="65334" weightExtensionRoad="2489" weightSpaceForVillage="41632" weightThiefMoveBase="94176" weightThiefMoveOtherBuilding="84667" weightThiefMoveMyBuilding="3525" weightThiefMoveProb="5366" weightVillageGeneral="99812" weightVillageGoodNumbers="80503" weightVillagePortThreeOne="24393" weightVillagePortTwoOne="14507" weightTownGeneral="68951" weightTownGoodNumbers="3342" weightBuyActionCardGeneral="43240" weightUseActionCardGeneral="2891" weightUseMatFromPlGeneral="94292" weightUseTwoMatRoadGeneral="59768" weightUseTwoMatVillageGeneral="88983" weightUseTwoMatTownGeneral="27748" weightUseTwoMatActGeneral="25282" weightUseTwoRoadGeneral="49238">
		<fitness>58</fitness>
	</param>
	<param weightGoodNumbers="32745" weightPortThreeOne="71007" weightPortTwoOne="5923" weightMissingMaterial="25803" weightEdgeGeneral="10084" weightWood="60374" weightBrick="65541" weightGrain="69150" weightSheep="58924" weightStone="83167" weightRoadGeneral="1971" weightLongestRoad="65334" weightExtensionRoad="2489" weightSpaceForVillage="41632" weightThiefMoveBase="94176" weightThiefMoveOtherBuilding="84667" weightThiefMoveMyBuilding="3525" weightThiefMoveProb="5366" weightVillageGeneral="99812" weightVillageGoodNumbers="80503" weightVillagePortThreeOne="24393" weightVillagePortTwoOne="14507" weightTownGeneral="68951" weightTownGoodNumbers="3342" weightBuyActionCardGeneral="43240" weightUseActionCardGeneral="2891" weightUseMatFromPlGeneral="94292" weightUseTwoMatRoadGeneral="64157" weightUseTwoMatVillageGeneral="52253" weightUseTwoMatTownGeneral="79812" weightUseTwoMatActGeneral="44470" weightUseTwoRoadGeneral="56679">
		<fitness>50</fitness>
	</param>
	<param weightGoodNumbers="32745" weightPortThreeOne="12099" weightPortTwoOne="79086" weightMissingMaterial="25803" weightEdgeGeneral="10084" weightWood="60374" weightBrick="65541" weightGrain="69150" weightSheep="58924" weightStone="83167" weightRoadGeneral="1971" weightLongestRoad="65334" weightExtensionRoad="87844" weightSpaceForVillage="41632" weightThiefMoveBase="94176" weightThiefMoveOtherBuilding="84667" weightThiefMoveMyBuilding="3525" weightThiefMoveProb="5366" weightVillageGeneral="99812" weightVillageGoodNumbers="5313" weightVillagePortThreeOne="76230" weightVillagePortTwoOne="14507" weightTownGeneral="68951" weightTownGoodNumbers="27418" weightBuyActionCardGeneral="43240" weightUseActionCardGeneral="2891" weightUseMatFromPlGeneral="94292" weightUseTwoMatRoadGeneral="64157" weightUseTwoMatVillageGeneral="52253" weightUseTwoMatTownGeneral="79812" weightUseTwoMatActGeneral="97825" weightUseTwoRoadGeneral="79684">
		<fitness>46</fitness>
	</param>
	<param weightGoodNumbers="32745" weightPortThreeOne="12099" weightPortTwoOne="79086" weightMissingMaterial="37929" weightEdgeGeneral="46977" weightWood="80142" weightBrick="65541" weightGrain="69150" weightSheep="58924" weightStone="83167" weightRoadGeneral="1971" weightLongestRoad="65334" weightExtensionRoad="2489" weightSpaceForVillage="41632" weightThiefMoveBase="48082" weightThiefMoveOtherBuilding="84667" weightThiefMoveMyBuilding="3525" weightThiefMoveProb="5366" weightVillageGeneral="99812" weightVillageGoodNumbers="80503" weightVillagePortThreeOne="24393" weightVillagePortTwoOne="14507" weightTownGeneral="68951" weightTownGoodNumbers="3342" weightBuyActionCardGeneral="43240" weightUseActionCardGeneral="2891" weightUseMatFromPlGeneral="94292" weightUseTwoMatRoadGeneral="64157" weightUseTwoMatVillageGeneral="52253" weightUseTwoMatTownGeneral="79812" weightUseTwoMatActGeneral="44470" weightUseTwoRoadGeneral="56679">
		<fitness>44</fitness>
	</param>
	<param weightGoodNumbers="32745" weightPortThreeOne="12099" weightPortTwoOne="79086" weightMissingMaterial="37929" weightEdgeGeneral="10084" weightWood="60374" weightBrick="65541" weightGrain="69150" weightSheep="58924" weightStone="83167" weightRoadGeneral="1971" weightLongestRoad="65334" weightExtensionRoad="2489" weightSpaceForVillage="41632" weightThiefMoveBase="94176" weightThiefMoveOtherBuilding="84667" weightThiefMoveMyBuilding="3525" weightThiefMoveProb="5366" weightVillageGeneral="99812" weightVillageGoodNumbers="80503" weightVillagePortThreeOne="24393" weightVillagePortTwoOne="14507" weightTownGeneral="68951" weightTownGoodNumbers="3342" weightBuyActionCardGeneral="43240" weightUseActionCardGeneral="2891" weightUseMatFromPlGeneral="94292" weightUseTwoMatRoadGeneral="59768" weightUseTwoMatVillageGeneral="88983" weightUseTwoMatTownGeneral="27748" weightUseTwoMatActGeneral="25282" weightUseTwoRoadGeneral="49238">
		<fitness>60</fitness>
	</param>
	<param weightGoodNumbers="32745" weightPortThreeOne="45113" weightPortTwoOne="79086" weightMissingMaterial="25803" weightEdgeGeneral="10084" weightWood="60374" weightBrick="65541" weightGrain="69150" weightSheep="58924" weightStone="83167" weightRoadGeneral="1971" weightLongestRoad="65334" weightExtensionRoad="2489" weightSpaceForVillage="41632" weightThiefMoveBase="94176" weightThiefMoveOtherBuilding="84667" weightThiefMoveMyBuilding="3525" weightThiefMoveProb="5366" weightVillageGeneral="99812" weightVillageGoodNumbers="80503" weightVillagePortThreeOne="24393" weightVillagePortTwoOne="14507" weightTownGeneral="68951" weightTownGoodNumbers="3342" weightBuyActionCardGeneral="43240" weightUseActionCardGeneral="2891" weightUseMatFromPlGeneral="94292" weightUseTwoMatRoadGeneral="64157" weightUseTwoMatVillageGeneral="52253" weightUseTwoMatTownGeneral="79812" weightUseTwoMatActGeneral="44470" weightUseTwoRoadGeneral="56679">
		<fitness>61</fitness>
	</param>
	<param weightGoodNumbers="32745" weightPortThreeOne="12099" weightPortTwoOne="79086" weightMissingMaterial="37929" weightEdgeGeneral="46977" weightWood="80142" weightBrick="65541" weightGrain="69150" weightSheep="58924" weightStone="83167" weightRoadGeneral="1971" weightLongestRoad="65334" weightExtensionRoad="2489" weightSpaceForVillage="41632" weightThiefMoveBase="48082" weightThiefMoveOtherBuilding="84667" weightThiefMoveMyBuilding="3525" weightThiefMoveProb="5366" weightVillageGeneral="99812" weightVillageGoodNumbers="80503" weightVillagePortThreeOne="24393" weightVillagePortTwoOne="14507" weightTownGeneral="68951" weightTownGoodNumbers="3342" weightBuyActionCardGeneral="43240" weightUseActionCardGeneral="2891" weightUseMatFromPlGeneral="94292" weightUseTwoMatRoadGeneral="64157" weightUseTwoMatVillageGeneral="52253" weightUseTwoMatTownGeneral="79812" weightUseTwoMatActGeneral="25282" weightUseTwoRoadGeneral="79684">
		<fitness>57</fitness>
	</param>
	<param weightGoodNumbers="32745" weightPortThreeOne="71007" weightPortTwoOne="5923" weightMissingMaterial="25803" weightEdgeGeneral="10084" weightWood="60374" weightBrick="65541" weightGrain="69150" weightSheep="58924" weightStone="83167" weightRoadGeneral="1971" weightLongestRoad="65334" weightExtensionRoad="2489" weightSpaceForVillage="41632" weightThiefMoveBase="94176" weightThiefMoveOtherBuilding="84667" weightThiefMoveMyBuilding="3525" weightThiefMoveProb="5366" weightVillageGeneral="99812" weightVillageGoodNumbers="80503" weightVillagePortThreeOne="24393" weightVillagePortTwoOne="14507" weightTownGeneral="68951" weightTownGoodNumbers="3342" weightBuyActionCardGeneral="43240" weightUseActionCardGeneral="2891" weightUseMatFromPlGeneral="94292" weightUseTwoMatRoadGeneral="64157" weightUseTwoMatVillageGeneral="52253" weightUseTwoMatTownGeneral="79812" weightUseTwoMatActGeneral="25282" weightUseTwoRoadGeneral="69481">
		<fitness>58</fitness>
	</param>
	<param weightGoodNumbers="32745" weightPortThreeOne="45113" weightPortTwoOne="79086" weightMissingMaterial="37929" weightEdgeGeneral="46977" weightWood="60374" weightBrick="65541" weightGrain="69150" weightSheep="58924" weightStone="83167" weightRoadGeneral="1971" weightLongestRoad="65334" weightExtensionRoad="2489" weightSpaceForVillage="41632" weightThiefMoveBase="94176" weightThiefMoveOtherBuilding="84667" weightThiefMoveMyBuilding="3525" weightThiefMoveProb="5366" weightVillageGeneral="99812" weightVillageGoodNumbers="80503" weightVillagePortThreeOne="24393" weightVillagePortTwoOne="14507" weightTownGeneral="68951" weightTownGoodNumbers="3342" weightBuyActionCardGeneral="43240" weightUseActionCardGeneral="2891" weightUseMatFromPlGeneral="94292" weightUseTwoMatRoadGeneral="64157" weightUseTwoMatVillageGeneral="52253" weightUseTwoMatTownGeneral="79812" weightUseTwoMatActGeneral="25282" weightUseTwoRoadGeneral="79684">
		<fitness>55</fitness>
	</param>
	<param weightGoodNumbers="32745" weightPortThreeOne="45113" weightPortTwoOne="79086" weightMissingMaterial="25803" weightEdgeGeneral="10084" weightWood="60374" weightBrick="65541" weightGrain="69150" weightSheep="58924" weightStone="83167" weightRoadGeneral="1971" weightLongestRoad="65334" weightExtensionRoad="2489" weightSpaceForVillage="41632" weightThiefMoveBase="94176" weightThiefMoveOtherBuilding="84667" weightThiefMoveMyBuilding="3525" weightThiefMoveProb="5366" weightVillageGeneral="99812" weightVillageGoodNumbers="80503" weightVillagePortThreeOne="24393" weightVillagePortTwoOne="14507" weightTownGeneral="68951" weightTownGoodNumbers="3342" weightBuyActionCardGeneral="43240" weightUseActionCardGeneral="2891" weightUseMatFromPlGeneral="94292" weightUseTwoMatRoadGeneral="64157" weightUseTwoMatVillageGeneral="52253" weightUseTwoMatTownGeneral="79812" weightUseTwoMatActGeneral="44470" weightUseTwoRoadGeneral="56679">
		<fitness>44</fitness>
	</param>
	<param weightGoodNumbers="32745" weightPortThreeOne="45113" weightPortTwoOne="79086" weightMissingMaterial="25803" weightEdgeGeneral="10084" weightWood="60374" weightBrick="65541" weightGrain="69150" weightSheep="58924" weightStone="83167" weightRoadGeneral="1971" weightLongestRoad="65334" weightExtensionRoad="2489" weightSpaceForVillage="41632" weightThiefMoveBase="94176" weightThiefMoveOtherBuilding="84667" weightThiefMoveMyBuilding="3525" weightThiefMoveProb="5366" weightVillageGeneral="99812" weightVillageGoodNumbers="80503" weightVillagePortThreeOne="24393" weightVillagePortTwoOne="14507" weightTownGeneral="68951" weightTownGoodNumbers="3342" weightBuyActionCardGeneral="43240" weightUseActionCardGeneral="2891" weightUseMatFromPlGeneral="94292" weightUseTwoMatRoadGeneral="64157" weightUseTwoMatVillageGeneral="52253" weightUseTwoMatTownGeneral="79812" weightUseTwoMatActGeneral="44470" weightUseTwoRoadGeneral="56679">
		<fitness>60</fitness>
	</param>
	<param weightGoodNumbers="32745" weightPortThreeOne="45113" weightPortTwoOne="79086" weightMissingMaterial="25803" weightEdgeGeneral="10084" weightWood="60374" weightBrick="65541" weightGrain="69150" weightSheep="58924" weightStone="83167" weightRoadGeneral="1971" weightLongestRoad="65334" weightExtensionRoad="2489" weightSpaceForVillage="41632" weightThiefMoveBase="94176" weightThiefMoveOtherBuilding="84667" weightThiefMoveMyBuilding="27155" weightThiefMoveProb="5366" weightVillageGeneral="99812" weightVillageGoodNumbers="80503" weightVillagePortThreeOne="24393" weightVillagePortTwoOne="14507" weightTownGeneral="68951" weightTownGoodNumbers="3342" weightBuyActionCardGeneral="43240" weightUseActionCardGeneral="2891" weightUseMatFromPlGeneral="94292" weightUseTwoMatRoadGeneral="59768" weightUseTwoMatVillageGeneral="88983" weightUseTwoMatTownGeneral="27748" weightUseTwoMatActGeneral="25282" weightUseTwoRoadGeneral="49238">
		<fitness>64</fitness>
	</param>
	<param weightGoodNumbers="32745" weightPortThreeOne="12099" weightPortTwoOne="79086" weightMissingMaterial="37929" weightEdgeGeneral="10084" weightWood="60374" weightBrick="65541" weightGrain="69150" weightSheep="58924" weightStone="83167" weightRoadGeneral="1971" weightLongestRoad="65334" weightExtensionRoad="30265" weightSpaceForVillage="41632" weightThiefMoveBase="13282" weightThiefMoveOtherBuilding="84667" weightThiefMoveMyBuilding="3525" weightThiefMoveProb="5366" weightVillageGeneral="77849" weightVillageGoodNumbers="80503" weightVillagePortThreeOne="24393" weightVillagePortTwoOne="14507" weightTownGeneral="68951" weightTownGoodNumbers="3342" weightBuyActionCardGeneral="48433" weightUseActionCardGeneral="2891" weightUseMatFromPlGeneral="94292" weightUseTwoMatRoadGeneral="59768" weightUseTwoMatVillageGeneral="88983" weightUseTwoMatTownGeneral="27748" weightUseTwoMatActGeneral="25282" weightUseTwoRoadGeneral="49238">
		<fitness>62</fitness>
	</param>
	<param weightGoodNumbers="32745" weightPortThreeOne="12099" weightPortTwoOne="79086" weightMissingMaterial="37929" weightEdgeGeneral="46977" weightWood="80142" weightBrick="65541" weightGrain="69150" weightSheep="58924" weightStone="83167" weightRoadGeneral="1971" weightLongestRoad="65334" weightExtensionRoad="2489" weightSpaceForVillage="41632" weightThiefMoveBase="48082" weightThiefMoveOtherBuilding="84667" weightThiefMoveMyBuilding="27155" weightThiefMoveProb="5366" weightVillageGeneral="99812" weightVillageGoodNumbers="80503" weightVillagePortThreeOne="24393" weightVillagePortTwoOne="14507" weightTownGeneral="68951" weightTownGoodNumbers="3342" weightBuyActionCardGeneral="43240" weightUseActionCardGeneral="2891" weightUseMatFromPlGeneral="94292" weightUseTwoMatRoadGeneral="59768" weightUseTwoMatVillageGeneral="88983" weightUseTwoMatTownGeneral="27748" weightUseTwoMatActGeneral="25282" weightUseTwoRoadGeneral="49238">
		<fitness>68</fitness>
	</param>
	<param weightGoodNumbers="32745" weightPortThreeOne="12099" weightPortTwoOne="79086" weightMissingMaterial="37929" weightEdgeGeneral="46977" weightWood="80142" weightBrick="65541" weightGrain="69150" weightSheep="58924" weightStone="83167" weightRoadGeneral="1971" weightLongestRoad="65334" weightExtensionRoad="2489" weightSpaceForVillage="41632" weightThiefMoveBase="94176" weightThiefMoveOtherBuilding="84667" weightThiefMoveMyBuilding="3525" weightThiefMoveProb="66576" weightVillageGeneral="99812" weightVillageGoodNumbers="80503" weightVillagePortThreeOne="24393" weightVillagePortTwoOne="14507" weightTownGeneral="68951" weightTownGoodNumbers="3342" weightBuyActionCardGeneral="43240" weightUseActionCardGeneral="2891" weightUseMatFromPlGeneral="94292" weightUseTwoMatRoadGeneral="64157" weightUseTwoMatVillageGeneral="52253" weightUseTwoMatTownGeneral="79812" weightUseTwoMatActGeneral="25282" weightUseTwoRoadGeneral="79684">
		<fitness>45</fitness>
	</param>
	<param weightGoodNumbers="32745" weightPortThreeOne="12099" weightPortTwoOne="79086" weightMissingMaterial="25803" weightEdgeGeneral="10084" weightWood="60374" weightBrick="65541" weightGrain="69150" weightSheep="58924" weightStone="83167" weightRoadGeneral="1971" weightLongestRoad="65334" weightExtensionRoad="2489" weightSpaceForVillage="41632" weightThiefMoveBase="94176" weightThiefMoveOtherBuilding="84667" weightThiefMoveMyBuilding="3525" weightThiefMoveProb="66576" weightVillageGeneral="99812" weightVillageGoodNumbers="80503" weightVillagePortThreeOne="24393" weightVillagePortTwoOne="14507" weightTownGeneral="68951" weightTownGoodNumbers="3342" weightBuyActionCardGeneral="43240" weightUseActionCardGeneral="2891" weightUseMatFromPlGeneral="94292" weightUseTwoMatRoadGeneral="64157" weightUseTwoMatVillageGeneral="52253" weightUseTwoMatTownGeneral="79812" weightUseTwoMatActGeneral="25282" weightUseTwoRoadGeneral="79684">
		<fitness>57</fitness>
	</param>
	<param weightGoodNumbers="32745" weightPortThreeOne="45113" weightPortTwoOne="79086" weightMissingMaterial="25803" weightEdgeGeneral="10084" weightWood="60374" weightBrick="65541" weightGrain="69150" weightSheep="58924" weightStone="83167" weightRoadGeneral="1971" weightLongestRoad="65334" weightExtensionRoad="2489" weightSpaceForVillage="41632" weightThiefMoveBase="94176" weightThiefMoveOtherBuilding="84667" weightThiefMoveMyBuilding="3525" weightThiefMoveProb="5366" weightVillageGeneral="99812" weightVillageGoodNumbers="80503" weightVillagePortThreeOne="24393" weightVillagePortTwoOne="14507" weightTownGeneral="68951" weightTownGoodNumbers="3342" weightBuyActionCardGeneral="43240" weightUseActionCardGeneral="2891" weightUseMatFromPlGeneral="94292" weightUseTwoMatRoadGeneral="59768" weightUseTwoMatVillageGeneral="88983" weightUseTwoMatTownGeneral="27748" weightUseTwoMatActGeneral="25282" weightUseTwoRoadGeneral="49238">
		<fitness>56</fitness>
	</param>
	<param weightGoodNumbers="32745" weightPortThreeOne="12099" weightPortTwoOne="79086" weightMissingMaterial="25803" weightEdgeGeneral="10084" weightWood="60374" weightBrick="65541" weightGrain="69150" weightSheep="58924" weightStone="83167" weightRoadGeneral="1971" weightLongestRoad="65334" weightExtensionRoad="2489" weightSpaceForVillage="41632" weightThiefMoveBase="94176" weightThiefMoveOtherBuilding="84667" weightThiefMoveMyBuilding="3525" weightThiefMoveProb="5366" weightVillageGeneral="99812" weightVillageGoodNumbers="80503" weightVillagePortThreeOne="24393" weightVillagePortTwoOne="14507" weightTownGeneral="68951" weightTownGoodNumbers="3342" weightBuyActionCardGeneral="43240" weightUseActionCardGeneral="2891" weightUseMatFromPlGeneral="94292" weightUseTwoMatRoadGeneral="64157" weightUseTwoMatVillageGeneral="52253" weightUseTwoMatTownGeneral="79812" weightUseTwoMatActGeneral="25282" weightUseTwoRoadGeneral="69481">
		<fitness>57</fitness>
	</param>
	<param weightGoodNumbers="32745" weightPortThreeOne="45113" weightPortTwoOne="79086" weightMissingMaterial="25803" weightEdgeGeneral="10084" weightWood="60374" weightBrick="65541" weightGrain="69150" weightSheep="58924" weightStone="83167" weightRoadGeneral="1971" weightLongestRoad="65334" weightExtensionRoad="2489" weightSpaceForVillage="41632" weightThiefMoveBase="94176" weightThiefMoveOtherBuilding="84667" weightThiefMoveMyBuilding="3525" weightThiefMoveProb="5366" weightVillageGeneral="99812" weightVillageGoodNumbers="80503" weightVillagePortThreeOne="24393" weightVillagePortTwoOne="14507" weightTownGeneral="68951" weightTownGoodNumbers="3342" weightBuyActionCardGeneral="43240" weightUseActionCardGeneral="2891" weightUseMatFromPlGeneral="94292" weightUseTwoMatRoadGeneral="64157" weightUseTwoMatVillageGeneral="52253" weightUseTwoMatTownGeneral="79812" weightUseTwoMatActGeneral="44470" weightUseTwoRoadGeneral="56679">
		<fitness>60</fitness>
	</param>
</population>
