<population>
	<param weightGoodNumbers="84213" weightPortThreeOne="29301" weightPortTwoOne="10514" weightMissingMaterial="98896" weightEdgeGeneral="68442" weightWood="16035" weightBrick="24907" weightGrain="8934" weightSheep="73626" weightStone="65658" weightRoadGeneral="7952" weightLongestRoad="7126" weightExtensionRoad="57117" weightSpaceForVillage="60689" weightThiefMoveBase="60369" weightThiefMoveOtherBuilding="5559" weightThiefMoveMyBuilding="97707" weightThiefMoveProb="62150" weightVillageGeneral="49086" weightVillageGoodNumbers="31911" weightVillagePortThreeOne="73613" weightVillagePortTwoOne="29293" weightTownGeneral="42340" weightTownGoodNumbers="60248" weightBuyActionCardGeneral="9616" weightUseActionCardGeneral="30766" weightUseMatFromPlGeneral="52169" weightUseTwoMatRoadGeneral="37354" weightUseTwoMatVillageGeneral="19889" weightUseTwoMatTownGeneral="39067" weightUseTwoMatActGeneral="68512" weightUseTwoRoadGeneral="99071">
		<fitness>55</fitness>
	</param>
	<param weightGoodNumbers="7774" weightPortThreeOne="688" weightPortTwoOne="28168" weightMissingMaterial="91958" weightEdgeGeneral="78780" weightWood="96338" weightBrick="52398" weightGrain="35910" weightSheep="12819" weightStone="6578" weightRoadGeneral="3748" weightLongestRoad="448" weightExtensionRoad="56713" weightSpaceForVillage="71916" weightThiefMoveBase="87479" weightThiefMoveOtherBuilding="73225" weightThiefMoveMyBuilding="69118" weightThiefMoveProb="17291" weightVillageGeneral="22560" weightVillageGoodNumbers="54128" weightVillagePortThreeOne="50791" weightVillagePortTwoOne="32713" weightTownGeneral="52671" weightTownGoodNumbers="54919" weightBuyActionCardGeneral="86961" weightUseActionCardGeneral="50266" weightUseMatFromPlGeneral="89279" weightUseTwoMatRoadGeneral="37675" weightUseTwoMatVillageGeneral="63867" weightUseTwoMatTownGeneral="87554" weightUseTwoMatActGeneral="89045" weightUseTwoRoadGeneral="34558">
		<fitness>50</fitness>
	</param>
	<param weightGoodNumbers="97146" weightPortThreeOne="8881" weightPortTwoOne="99353" weightMissingMaterial="56429" weightEdgeGeneral="32521" weightWood="68412" weightBrick="26779" weightGrain="1369" weightSheep="9752" weightStone="13175" weightRoadGeneral="19091" weightLongestRoad="67034" weightExtensionRoad="25545" weightSpaceForVillage="41892" weightThiefMoveBase="3535" weightThiefMoveOtherBuilding="37700" weightThiefMoveMyBuilding="43288" weightThiefMoveProb="78945" weightVillageGeneral="68237" weightVillageGoodNumbers="2597" weightVillagePortThreeOne="16507" weightVillagePortTwoOne="14384" weightTownGeneral="48279" weightTownGoodNumbers="75062" weightBuyActionCardGeneral="48018" weightUseActionCardGeneral="73249" weightUseMatFromPlGeneral="4996" weightUseTwoMatRoadGeneral="28514" weightUseTwoMatVillageGeneral="7058" weightUseTwoMatTownGeneral="14722" weightUseTwoMatActGeneral="72044" weightUseTwoRoadGeneral="25266">
		<fitness>56</fitness>
	</param>
	<param weightGoodNumbers="17533" weightPortThreeOne="69190" weightPortTwoOne="3302" weightMissingMaterial="47831" weightEdgeGeneral="72564" weightWood="31049" weightBrick="40703" weightGrain="705" weightSheep="90512" weightStone="21191" weightRoadGeneral="44376" weightLongestRoad="37616" weightExtensionRoad="13622" weightSpaceForVillage="85637" weightThiefMoveBase="29374" weightThiefMoveOtherBuilding="45069" weightThiefMoveMyBuilding="46730" weightThiefMoveProb="51579" weightVillageGeneral="94388" weightVillageGoodNumbers="84923" weightVillagePortThreeOne="19317" weightVillagePortTwoOne="86447" weightTownGeneral="18051" weightTownGoodNumbers="82762" weightBuyActionCardGeneral="60603" weightUseActionCardGeneral="24290" weightUseMatFromPlGeneral="8410" weightUseTwoMatRoadGeneral="59273" weightUseTwoMatVillageGeneral="63416" weightUseTwoMatTownGeneral="98266" weightUseTwoMatActGeneral="94311" weightUseTwoRoadGeneral="95030">
		<fitness>31</fitness>
	</param>
	<param weightGoodNumbers="41132" weightPortThreeOne="93825" weightPortTwoOne="49500" weightMissingMaterial="56356" weightEdgeGeneral="38590" weightWood="55705" weightBrick="65136" weightGrain="12238" weightSheep="38241" weightStone="67531" weightRoadGeneral="12085" weightLongestRoad="95316" weightExtensionRoad="70008" weightSpaceForVillage="10663" weightThiefMoveBase="61440" weightThiefMoveOtherBuilding="62381" weightThiefMoveMyBuilding="43874" weightThiefMoveProb="59928" weightVillageGeneral="81784" weightVillageGoodNumbers="55480" weightVillagePortThreeOne="20334" weightVillagePortTwoOne="87122" weightTownGeneral="5949" weightTownGoodNumbers="31087" weightBuyActionCardGeneral="51138" weightUseActionCardGeneral="20540" weightUseMatFromPlGeneral="87229" weightUseTwoMatRoadGeneral="48274" weightUseTwoMatVillageGeneral="22638" weightUseTwoMatTownGeneral="81430" weightUseTwoMatActGeneral="37290" weightUseTwoRoadGeneral="92247">
		<fitness>78</fitness>
	</param>
	<param weightGoodNumbers="26880" weightPortThreeOne="49347" weightPortTwoOne="96484" weightMissingMaterial="19797" weightEdgeGeneral="36137" weightWood="73019" weightBrick="6478" weightGrain="91026" weightSheep="86443" weightStone="82150" weightRoadGeneral="46681" weightLongestRoad="51787" weightExtensionRoad="74362" weightSpaceForVillage="22735" weightThiefMoveBase="12754" weightThiefMoveOtherBuilding="49939" weightThiefMoveMyBuilding="62851" weightThiefMoveProb="46030" weightVillageGeneral="15398" weightVillageGoodNumbers="3487" weightVillagePortThreeOne="16482" weightVillagePortTwoOne="38831" weightTownGeneral="74695" weightTownGoodNumbers="54011" weightBuyActionCardGeneral="87876" weightUseActionCardGeneral="18413" weightUseMatFromPlGeneral="5217" weightUseTwoMatRoadGeneral="18050" weightUseTwoMatVillageGeneral="68476" weightUseTwoMatTownGeneral="16862" weightUseTwoMatActGeneral="89600" weightUseTwoRoadGeneral="56811">
		<fitness>61</fitness>
	</param>
	<param weightGoodNumbers="30240" weightPortThreeOne="19839" weightPortTwoOne="68436" weightMissingMaterial="20661" weightEdgeGeneral="14179" weightWood="41642" weightBrick="26244" weightGrain="70856" weightSheep="53449" weightStone="90758" weightRoadGeneral="69037" weightLongestRoad="38185" weightExtensionRoad="40440" weightSpaceForVillage="54163" weightThiefMoveBase="56726" weightThiefMoveOtherBuilding="28403" weightThiefMoveMyBuilding="7786" weightThiefMoveProb="37290" weightVillageGeneral="85423" weightVillageGoodNumbers="76609" weightVillagePortThreeOne="66032" weightVillagePortTwoOne="33802" weightTownGeneral="75764" weightTownGoodNumbers="88049" weightBuyActionCardGeneral="74653" weightUseActionCardGeneral="42473" weightUseMatFromPlGeneral="31921" weightUseTwoMatRoadGeneral="17723" weightUseTwoMatVillageGeneral="67802" weightUseTwoMatTownGeneral="88429" weightUseTwoMatActGeneral="22550" weightUseTwoRoadGeneral="69581">
		<fitness>103</fitness>
	</param>
	<param weightGoodNumbers="92551" weightPortThreeOne="89871" weightPortTwoOne="21546" weightMissingMaterial="54522" weightEdgeGeneral="54300" weightWood="92093" weightBrick="35759" weightGrain="21208" weightSheep="19785" weightStone="44543" weightRoadGeneral="50038" weightLongestRoad="25725" weightExtensionRoad="69795" weightSpaceForVillage="36510" weightThiefMoveBase="13570" weightThiefMoveOtherBuilding="33713" weightThiefMoveMyBuilding="61688" weightThiefMoveProb="76814" weightVillageGeneral="10263" weightVillageGoodNumbers="31186" weightVillagePortThreeOne="31439" weightVillagePortTwoOne="12990" weightTownGeneral="90780" weightTownGoodNumbers="96438" weightBuyActionCardGeneral="44075" weightUseActionCardGeneral="80387" weightUseMatFromPlGeneral="46009" weightUseTwoMatRoadGeneral="71707" weightUseTwoMatVillageGeneral="9721" weightUseTwoMatTownGeneral="8521" weightUseTwoMatActGeneral="3054" weightUseTwoRoadGeneral="65021">
		<fitness>60</fitness>
	</param>
	<param weightGoodNumbers="68207" weightPortThreeOne="99457" weightPortTwoOne="45635" weightMissingMaterial="50570" weightEdgeGeneral="32616" weightWood="2203" weightBrick="74103" weightGrain="15693" weightSheep="1530" weightStone="64214" weightRoadGeneral="56824" weightLongestRoad="21488" weightExtensionRoad="83765" weightSpaceForVillage="50039" weightThiefMoveBase="18254" weightThiefMoveOtherBuilding="38142" weightThiefMoveMyBuilding="28903" weightThiefMoveProb="98209" weightVillageGeneral="56036" weightVillageGoodNumbers="90988" weightVillagePortThreeOne="78165" weightVillagePortTwoOne="91365" weightTownGeneral="38141" weightTownGoodNumbers="79560" weightBuyActionCardGeneral="99091" weightUseActionCardGeneral="25109" weightUseMatFromPlGeneral="10446" weightUseTwoMatRoadGeneral="73914" weightUseTwoMatVillageGeneral="46084" weightUseTwoMatTownGeneral="64053" weightUseTwoMatActGeneral="11487" weightUseTwoRoadGeneral="11263">
		<fitness>51</fitness>
	</param>
	<param weightGoodNumbers="41489" weightPortThreeOne="85018" weightPortTwoOne="57518" weightMissingMaterial="70339" weightEdgeGeneral="90875" weightWood="63000" weightBrick="1097" weightGrain="59484" weightSheep="2711" weightStone="94571" weightRoadGeneral="29655" weightLongestRoad="67226" weightExtensionRoad="56167" weightSpaceForVillage="69291" weightThiefMoveBase="12673" weightThiefMoveOtherBuilding="94036" weightThiefMoveMyBuilding="62132" weightThiefMoveProb="7866" weightVillageGeneral="42804" weightVillageGoodNumbers="11512" weightVillagePortThreeOne="52486" weightVillagePortTwoOne="12066" weightTownGeneral="86856" weightTownGoodNumbers="76843" weightBuyActionCardGeneral="61315" weightUseActionCardGeneral="66076" weightUseMatFromPlGeneral="51479" weightUseTwoMatRoadGeneral="7506" weightUseTwoMatVillageGeneral="91757" weightUseTwoMatTownGeneral="189" weightUseTwoMatActGeneral="69609" weightUseTwoRoadGeneral="37478">
		<fitness>67</fitness>
	</param>
	<param weightGoodNumbers="52727" weightPortThreeOne="45560" weightPortTwoOne="80000" weightMissingMaterial="98747" weightEdgeGeneral="92522" weightWood="47916" weightBrick="47267" weightGrain="65903" weightSheep="97112" weightStone="96552" weightRoadGeneral="88277" weightLongestRoad="83595" weightExtensionRoad="61709" weightSpaceForVillage="70916" weightThiefMoveBase="23392" weightThiefMoveOtherBuilding="29800" weightThiefMoveMyBuilding="12436" weightThiefMoveProb="16410" weightVillageGeneral="11781" weightVillageGoodNumbers="38218" weightVillagePortThreeOne="21249" weightVillagePortTwoOne="99976" weightTownGeneral="58778" weightTownGoodNumbers="29422" weightBuyActionCardGeneral="98163" weightUseActionCardGeneral="80675" weightUseMatFromPlGeneral="9023" weightUseTwoMatRoadGeneral="24799" weightUseTwoMatVillageGeneral="11520" weightUseTwoMatTownGeneral="93591" weightUseTwoMatActGeneral="67728" weightUseTwoRoadGeneral="2521">
		<fitness>68</fitness>
	</param>
	<param weightGoodNumbers="24961" weightPortThreeOne="92178" weightPortTwoOne="14498" weightMissingMaterial="10606" weightEdgeGeneral="89292" weightWood="13926" weightBrick="1514" weightGrain="14215" weightSheep="60599" weightStone="76902" weightRoadGeneral="14400" weightLongestRoad="55935" weightExtensionRoad="23790" weightSpaceForVillage="3260" weightThiefMoveBase="15134" weightThiefMoveOtherBuilding="90400" weightThiefMoveMyBuilding="42683" weightThiefMoveProb="21679" weightVillageGeneral="95071" weightVillageGoodNumbers="75346" weightVillagePortThreeOne="88408" weightVillagePortTwoOne="31391" weightTownGeneral="16229" weightTownGoodNumbers="52752" weightBuyActionCardGeneral="86783" weightUseActionCardGeneral="50577" weightUseMatFromPlGeneral="584" weightUseTwoMatRoadGeneral="11847" weightUseTwoMatVillageGeneral="38893" weightUseTwoMatTownGeneral="22468" weightUseTwoMatActGeneral="54382" weightUseTwoRoadGeneral="3521">
		<fitness>63</fitness>
	</param>
	<param weightGoodNumbers="28823" weightPortThreeOne="85755" weightPortTwoOne="58633" weightMissingMaterial="69531" weightEdgeGeneral="56417" weightWood="12786" weightBrick="40509" weightGrain="98510" weightSheep="14896" weightStone="97566" weightRoadGeneral="77619" weightLongestRoad="44347" weightExtensionRoad="85575" weightSpaceForVillage="2843" weightThiefMoveBase="5632" weightThiefMoveOtherBuilding="94902" weightThiefMoveMyBuilding="65540" weightThiefMoveProb="18623" weightVillageGeneral="82117" weightVillageGoodNumbers="89842" weightVillagePortThreeOne="98521" weightVillagePortTwoOne="92382" weightTownGeneral="14113" weightTownGoodNumbers="93571" weightBuyActionCardGeneral="75949" weightUseActionCardGeneral="61747" weightUseMatFromPlGeneral="23824" weightUseTwoMatRoadGeneral="38714" weightUseTwoMatVillageGeneral="13342" weightUseTwoMatTownGeneral="89667" weightUseTwoMatActGeneral="75323" weightUseTwoRoadGeneral="38131">
		<fitness>73</fitness>
	</param>
	<param weightGoodNumbers="22519" weightPortThreeOne="10879" weightPortTwoOne="27111" weightMissingMaterial="38035" weightEdgeGeneral="44627" weightWood="45604" weightBrick="33983" weightGrain="29897" weightSheep="81171" weightStone="96561" weightRoadGeneral="60450" weightLongestRoad="90843" weightExtensionRoad="53772" weightSpaceForVillage="71882" weightThiefMoveBase="67178" weightThiefMoveOtherBuilding="83940" weightThiefMoveMyBuilding="44945" weightThiefMoveProb="5682" weightVillageGeneral="46307" weightVillageGoodNumbers="20269" weightVillagePortThreeOne="40351" weightVillagePortTwoOne="64541" weightTownGeneral="5000" weightTownGoodNumbers="36442" weightBuyActionCardGeneral="71642" weightUseActionCardGeneral="65063" weightUseMatFromPlGeneral="93583" weightUseTwoMatRoadGeneral="94670" weightUseTwoMatVillageGeneral="88962" weightUseTwoMatTownGeneral="1794" weightUseTwoMatActGeneral="85167" weightUseTwoRoadGeneral="25229">
		<fitness>50</fitness>
	</param>
	<param weightGoodNumbers="22243" weightPortThreeOne="39488" weightPortTwoOne="21827" weightMissingMaterial="74695" weightEdgeGeneral="75732" weightWood="67597" weightBrick="50274" weightGrain="19936" weightSheep="84641" weightStone="52220" weightRoadGeneral="8670" weightLongestRoad="1959" weightExtensionRoad="31932" weightSpaceForVillage="23271" weightThiefMoveBase="39799" weightThiefMoveOtherBuilding="4067" weightThiefMoveMyBuilding="94570" weightThiefMoveProb="39885" weightVillageGeneral="93769" weightVillageGoodNumbers="7659" weightVillagePortThreeOne="43360" weightVillagePortTwoOne="55053" weightTownGeneral="97780" weightTownGoodNumbers="57979" weightBuyActionCardGeneral="5878" weightUseActionCardGeneral="90669" weightUseMatFromPlGeneral="66394" weightUseTwoMatRoadGeneral="79565" weightUseTwoMatVillageGeneral="52021" weightUseTwoMatTownGeneral="39313" weightUseTwoMatActGeneral="40935" weightUseTwoRoadGeneral="79376">
		<fitness>84</fitness>
	</param>
	<param weightGoodNumbers="11393" weightPortThreeOne="35220" weightPortTwoOne="68600" weightMissingMaterial="14283" weightEdgeGeneral="50054" weightWood="92483" weightBrick="8207" weightGrain="77349" weightSheep="55409" weightStone="26371" weightRoadGeneral="35629" weightLongestRoad="88132" weightExtensionRoad="55870" weightSpaceForVillage="3041" weightThiefMoveBase="4510" weightThiefMoveOtherBuilding="48370" weightThiefMoveMyBuilding="25264" weightThiefMoveProb="89516" weightVillageGeneral="100" weightVillageGoodNumbers="49077" weightVillagePortThreeOne="8026" weightVillagePortTwoOne="77508" weightTownGeneral="81870" weightTownGoodNumbers="67190" weightBuyActionCardGeneral="41708" weightUseActionCardGeneral="63848" weightUseMatFromPlGeneral="68816" weightUseTwoMatRoadGeneral="85064" weightUseTwoMatVillageGeneral="1202" weightUseTwoMatTownGeneral="70709" weightUseTwoMatActGeneral="67915" weightUseTwoRoadGeneral="45327">
		<fitness>44</fitness>
	</param>
	<param weightGoodNumbers="11284" weightPortThreeOne="29294" weightPortTwoOne="90566" weightMissingMaterial="96712" weightEdgeGeneral="54672" weightWood="25515" weightBrick="54013" weightGrain="2086" weightSheep="31678" weightStone="16419" weightRoadGeneral="52251" weightLongestRoad="16988" weightExtensionRoad="19423" weightSpaceForVillage="9648" weightThiefMoveBase="2109" weightThiefMoveOtherBuilding="2837" weightThiefMoveMyBuilding="86158" weightThiefMoveProb="18024" weightVillageGeneral="54300" weightVillageGoodNumbers="62506" weightVillagePortThreeOne="39213" weightVillagePortTwoOne="91858" weightTownGeneral="71350" weightTownGoodNumbers="33886" weightBuyActionCardGeneral="53350" weightUseActionCardGeneral="1409" weightUseMatFromPlGeneral="72575" weightUseTwoMatRoadGeneral="86206" weightUseTwoMatVillageGeneral="23667" weightUseTwoMatTownGeneral="23143" weightUseTwoMatActGeneral="76146" weightUseTwoRoadGeneral="84700">
		<fitness>75</fitness>
	</param>
	<param weightGoodNumbers="58456" weightPortThreeOne="90302" weightPortTwoOne="76847" weightMissingMaterial="26575" weightEdgeGeneral="12475" weightWood="7799" weightBrick="93699" weightGrain="99750" weightSheep="35502" weightStone="98014" weightRoadGeneral="17399" weightLongestRoad="91607" weightExtensionRoad="25257" weightSpaceForVillage="64881" weightThiefMoveBase="47766" weightThiefMoveOtherBuilding="32060" weightThiefMoveMyBuilding="61739" weightThiefMoveProb="65978" weightVillageGeneral="98906" weightVillageGoodNumbers="83179" weightVillagePortThreeOne="16409" weightVillagePortTwoOne="5408" weightTownGeneral="6114" weightTownGoodNumbers="19426" weightBuyActionCardGeneral="57945" weightUseActionCardGeneral="56680" weightUseMatFromPlGeneral="43361" weightUseTwoMatRoadGeneral="53263" weightUseTwoMatVillageGeneral="52940" weightUseTwoMatTownGeneral="67808" weightUseTwoMatActGeneral="78420" weightUseTwoRoadGeneral="8534">
		<fitness>83</fitness>
	</param>
	<param weightGoodNumbers="40273" weightPortThreeOne="67551" weightPortTwoOne="58533" weightMissingMaterial="29122" weightEdgeGeneral="32801" weightWood="75534" weightBrick="90363" weightGrain="78359" weightSheep="24325" weightStone="54551" weightRoadGeneral="27004" weightLongestRoad="41199" weightExtensionRoad="74459" weightSpaceForVillage="79743" weightThiefMoveBase="8629" weightThiefMoveOtherBuilding="88469" weightThiefMoveMyBuilding="53643" weightThiefMoveProb="40515" weightVillageGeneral="24466" weightVillageGoodNumbers="57690" weightVillagePortThreeOne="24238" weightVillagePortTwoOne="92968" weightTownGeneral="68291" weightTownGoodNumbers="53047" weightBuyActionCardGeneral="84187" weightUseActionCardGeneral="57420" weightUseMatFromPlGeneral="68630" weightUseTwoMatRoadGeneral="55795" weightUseTwoMatVillageGeneral="64438" weightUseTwoMatTownGeneral="40436" weightUseTwoMatActGeneral="46810" weightUseTwoRoadGeneral="67695">
		<fitness>72</fitness>
	</param>
	<param weightGoodNumbers="19594" weightPortThreeOne="8864" weightPortTwoOne="51333" weightMissingMaterial="57706" weightEdgeGeneral="6348" weightWood="18644" weightBrick="99259" weightGrain="86205" weightSheep="75616" weightStone="20546" weightRoadGeneral="58853" weightLongestRoad="61858" weightExtensionRoad="78405" weightSpaceForVillage="64916" weightThiefMoveBase="44968" weightThiefMoveOtherBuilding="78203" weightThiefMoveMyBuilding="48051" weightThiefMoveProb="54892" weightVillageGeneral="99620" weightVillageGoodNumbers="12424" weightVillagePortThreeOne="43341" weightVillagePortTwoOne="20729" weightTownGeneral="84297" weightTownGoodNumbers="47306" weightBuyActionCardGeneral="99260" weightUseActionCardGeneral="5485" weightUseMatFromPlGeneral="44935" weightUseTwoMatRoadGeneral="75381" weightUseTwoMatVillageGeneral="6903" weightUseTwoMatTownGeneral="34567" weightUseTwoMatActGeneral="13921" weightUseTwoRoadGeneral="83890">
		<fitness>44</fitness>
	</param>
	<param weightGoodNumbers="7741" weightPortThreeOne="59309" weightPortTwoOne="21605" weightMissingMaterial="65595" weightEdgeGeneral="28409" weightWood="50923" weightBrick="82121" weightGrain="34999" weightSheep="41256" weightStone="38261" weightRoadGeneral="82075" weightLongestRoad="3691" weightExtensionRoad="34114" weightSpaceForVillage="6432" weightThiefMoveBase="74642" weightThiefMoveOtherBuilding="19271" weightThiefMoveMyBuilding="12452" weightThiefMoveProb="90428" weightVillageGeneral="7744" weightVillageGoodNumbers="9545" weightVillagePortThreeOne="40816" weightVillagePortTwoOne="34385" weightTownGeneral="24354" weightTownGoodNumbers="98865" weightBuyActionCardGeneral="24568" weightUseActionCardGeneral="4027" weightUseMatFromPlGeneral="58447" weightUseTwoMatRoadGeneral="862" weightUseTwoMatVillageGeneral="73709" weightUseTwoMatTownGeneral="23877" weightUseTwoMatActGeneral="79302" weightUseTwoRoadGeneral="41048">
		<fitness>66</fitness>
	</param>
	<param weightGoodNumbers="6625" weightPortThreeOne="74964" weightPortTwoOne="54117" weightMissingMaterial="19096" weightEdgeGeneral="43310" weightWood="79373" weightBrick="49794" weightGrain="97128" weightSheep="72772" weightStone="64621" weightRoadGeneral="71168" weightLongestRoad="5079" weightExtensionRoad="38655" weightSpaceForVillage="80606" weightThiefMoveBase="13191" weightThiefMoveOtherBuilding="92827" weightThiefMoveMyBuilding="30844" weightThiefMoveProb="25663" weightVillageGeneral="62929" weightVillageGoodNumbers="16476" weightVillagePortThreeOne="26822" weightVillagePortTwoOne="4376" weightTownGeneral="43073" weightTownGoodNumbers="73356" weightBuyActionCardGeneral="34955" weightUseActionCardGeneral="22740" weightUseMatFromPlGeneral="41027" weightUseTwoMatRoadGeneral="24381" weightUseTwoMatVillageGeneral="92477" weightUseTwoMatTownGeneral="81259" weightUseTwoMatActGeneral="61290" weightUseTwoRoadGeneral="17379">
		<fitness>62</fitness>
	</param>
	<param weightGoodNumbers="58960" weightPortThreeOne="41026" weightPortTwoOne="97067" weightMissingMaterial="59150" weightEdgeGeneral="52316" weightWood="55546" weightBrick="75962" weightGrain="33079" weightSheep="40633" weightStone="10617" weightRoadGeneral="36774" weightLongestRoad="76196" weightExtensionRoad="63217" weightSpaceForVillage="19274" weightThiefMoveBase="60209" weightThiefMoveOtherBuilding="43962" weightThiefMoveMyBuilding="90836" weightThiefMoveProb="65620" weightVillageGeneral="70019" weightVillageGoodNumbers="48045" weightVillagePortThreeOne="60949" weightVillagePortTwoOne="62825" weightTownGeneral="14225" weightTownGoodNumbers="2248" weightBuyActionCardGeneral="31891" weightUseActionCardGeneral="80761" weightUseMatFromPlGeneral="84141" weightUseTwoMatRoadGeneral="20569" weightUseTwoMatVillageGeneral="38346" weightUseTwoMatTownGeneral="25412" weightUseTwoMatActGeneral="4651" weightUseTwoRoadGeneral="91514">
		<fitness>90</fitness>
	</param>
	<param weightGoodNumbers="3330" weightPortThreeOne="53789" weightPortTwoOne="46119" weightMissingMaterial="97630" weightEdgeGeneral="83539" weightWood="54041" weightBrick="40511" weightGrain="75298" weightSheep="49702" weightStone="29849" weightRoadGeneral="75843" weightLongestRoad="16205" weightExtensionRoad="67603" weightSpaceForVillage="66877" weightThiefMoveBase="10139" weightThiefMoveOtherBuilding="15680" weightThiefMoveMyBuilding="62532" weightThiefMoveProb="97065" weightVillageGeneral="33546" weightVillageGoodNumbers="26856" weightVillagePortThreeOne="11240" weightVillagePortTwoOne="13244" weightTownGeneral="56430" weightTownGoodNumbers="96136" weightBuyActionCardGeneral="26800" weightUseActionCardGeneral="94818" weightUseMatFromPlGeneral="27259" weightUseTwoMatRoadGeneral="71555" weightUseTwoMatVillageGeneral="71406" weightUseTwoMatTownGeneral="55392" weightUseTwoMatActGeneral="94733" weightUseTwoRoadGeneral="15221">
		<fitness>55</fitness>
	</param>
	<param weightGoodNumbers="5965" weightPortThreeOne="45260" weightPortTwoOne="72865" weightMissingMaterial="9428" weightEdgeGeneral="73156" weightWood="62580" weightBrick="60424" weightGrain="36794" weightSheep="25108" weightStone="94721" weightRoadGeneral="98343" weightLongestRoad="31100" weightExtensionRoad="86982" weightSpaceForVillage="98021" weightThiefMoveBase="34646" weightThiefMoveOtherBuilding="65014" weightThiefMoveMyBuilding="70622" weightThiefMoveProb="68460" weightVillageGeneral="58038" weightVillageGoodNumbers="41282" weightVillagePortThreeOne="91867" weightVillagePortTwoOne="77795" weightTownGeneral="80273" weightTownGoodNumbers="90086" weightBuyActionCardGeneral="97359" weightUseActionCardGeneral="49983" weightUseMatFromPlGeneral="70829" weightUseTwoMatRoadGeneral="88722" weightUseTwoMatVillageGeneral="26782" weightUseTwoMatTownGeneral="68957" weightUseTwoMatActGeneral="3892" weightUseTwoRoadGeneral="94311">
		<fitness>69</fitness>
	</param>
	<param weightGoodNumbers="35116" weightPortThreeOne="60622" weightPortTwoOne="10240" weightMissingMaterial="22342" weightEdgeGeneral="94013" weightWood="710" weightBrick="42525" weightGrain="99952" weightSheep="36641" weightStone="96752" weightRoadGeneral="1748" weightLongestRoad="16519" weightExtensionRoad="14902" weightSpaceForVillage="25330" weightThiefMoveBase="9153" weightThiefMoveOtherBuilding="28780" weightThiefMoveMyBuilding="60171" weightThiefMoveProb="62246" weightVillageGeneral="932" weightVillageGoodNumbers="2945" weightVillagePortThreeOne="97354" weightVillagePortTwoOne="53451" weightTownGeneral="23355" weightTownGoodNumbers="28170" weightBuyActionCardGeneral="64987" weightUseActionCardGeneral="82779" weightUseMatFromPlGeneral="12069" weightUseTwoMatRoadGeneral="23172" weightUseTwoMatVillageGeneral="91752" weightUseTwoMatTownGeneral="71702" weightUseTwoMatActGeneral="10012" weightUseTwoRoadGeneral="56151">
		<fitness>90</fitness>
	</param>
	<param weightGoodNumbers="90828" weightPortThreeOne="4031" weightPortTwoOne="95985" weightMissingMaterial="26360" weightEdgeGeneral="87780" weightWood="12304" weightBrick="71002" weightGrain="69911" weightSheep="25935" weightStone="58087" weightRoadGeneral="4641" weightLongestRoad="95116" weightExtensionRoad="76047" weightSpaceForVillage="63754" weightThiefMoveBase="75184" weightThiefMoveOtherBuilding="72029" weightThiefMoveMyBuilding="40829" weightThiefMoveProb="42048" weightVillageGeneral="28550" weightVillageGoodNumbers="64537" weightVillagePortThreeOne="68024" weightVillagePortTwoOne="947" weightTownGeneral="96958" weightTownGoodNumbers="81666" weightBuyActionCardGeneral="37266" weightUseActionCardGeneral="82070" weightUseMatFromPlGeneral="57355" weightUseTwoMatRoadGeneral="11233" weightUseTwoMatVillageGeneral="88642" weightUseTwoMatTownGeneral="19352" weightUseTwoMatActGeneral="8200" weightUseTwoRoadGeneral="64939">
		<fitness>83</fitness>
	</param>
	<param weightGoodNumbers="86739" weightPortThreeOne="45597" weightPortTwoOne="25691" weightMissingMaterial="10870" weightEdgeGeneral="29346" weightWood="82794" weightBrick="41000" weightGrain="47867" weightSheep="91244" weightStone="31021" weightRoadGeneral="77010" weightLongestRoad="39266" weightExtensionRoad="48809" weightSpaceForVillage="28240" weightThiefMoveBase="52124" weightThiefMoveOtherBuilding="1233" weightThiefMoveMyBuilding="7594" weightThiefMoveProb="40040" weightVillageGeneral="82343" weightVillageGoodNumbers="49704" weightVillagePortThreeOne="43152" weightVillagePortTwoOne="45476" weightTownGeneral="88127" weightTownGoodNumbers="89881" weightBuyActionCardGeneral="7074" weightUseActionCardGeneral="14319" weightUseMatFromPlGeneral="89094" weightUseTwoMatRoadGeneral="5710" weightUseTwoMatVillageGeneral="54949" weightUseTwoMatTownGeneral="59768" weightUseTwoMatActGeneral="81270" weightUseTwoRoadGeneral="6582">
		<fitness>59</fitness>
	</param>
	<param weightGoodNumbers="49887" weightPortThreeOne="39703" weightPortTwoOne="8376" weightMissingMaterial="30449" weightEdgeGeneral="38062" weightWood="64314" weightBrick="42683" weightGrain="58036" weightSheep="1047" weightStone="80684" weightRoadGeneral="73293" weightLongestRoad="37003" weightExtensionRoad="23937" weightSpaceForVillage="57692" weightThiefMoveBase="32856" weightThiefMoveOtherBuilding="9026" weightThiefMoveMyBuilding="29945" weightThiefMoveProb="56121" weightVillageGeneral="3638" weightVillageGoodNumbers="48601" weightVillagePortThreeOne="37010" weightVillagePortTwoOne="58497" weightTownGeneral="21787" weightTownGoodNumbers="41263" weightBuyActionCardGeneral="57471" weightUseActionCardGeneral="35811" weightUseMatFromPlGeneral="3796" weightUseTwoMatRoadGeneral="15027" weightUseTwoMatVillageGeneral="93701" weightUseTwoMatTownGeneral="35290" weightUseTwoMatActGeneral="92918" weightUseTwoRoadGeneral="31476">
		<fitness>56</fitness>
	</param>
	<param weightGoodNumbers="49752" weightPortThreeOne="70427" weightPortTwoOne="89380" weightMissingMaterial="9106" weightEdgeGeneral="19863" weightWood="21675" weightBrick="63171" weightGrain="43280" weightSheep="97358" weightStone="24306" weightRoadGeneral="48656" weightLongestRoad="62468" weightExtensionRoad="72183" weightSpaceForVillage="51124" weightThiefMoveBase="65943" weightThiefMoveOtherBuilding="49382" weightThiefMoveMyBuilding="81463" weightThiefMoveProb="80067" weightVillageGeneral="75766" weightVillageGoodNumbers="98829" weightVillagePortThreeOne="56129" weightVillagePortTwoOne="32669" weightTownGeneral="69573" weightTownGoodNumbers="91391" weightBuyActionCardGeneral="17916" weightUseActionCardGeneral="67113" weightUseMatFromPlGeneral="72979" weightUseTwoMatRoadGeneral="2251" weightUseTwoMatVillageGeneral="60518" weightUseTwoMatTownGeneral="27656" weightUseTwoMatActGeneral="64336" weightUseTwoRoadGeneral="65758">
		<fitness>45</fitness>
	</param>
	<param weightGoodNumbers="87766" weightPortThreeOne="41817" weightPortTwoOne="87251" weightMissingMaterial="53511" weightEdgeGeneral="68313" weightWood="23750" weightBrick="89163" weightGrain="8269" weightSheep="92950" weightStone="60358" weightRoadGeneral="51243" weightLongestRoad="12703" weightExtensionRoad="9840" weightSpaceForVillage="59319" weightThiefMoveBase="69081" weightThiefMoveOtherBuilding="6346" weightThiefMoveMyBuilding="69868" weightThiefMoveProb="54414" weightVillageGeneral="33564" weightVillageGoodNumbers="13633" weightVillagePortThreeOne="59524" weightVillagePortTwoOne="94090" weightTownGeneral="75347" weightTownGoodNumbers="17083" weightBuyActionCardGeneral="854" weightUseActionCardGeneral="97989" weightUseMatFromPlGeneral="91190" weightUseTwoMatRoadGeneral="52751" weightUseTwoMatVillageGeneral="48697" weightUseTwoMatTownGeneral="60920" weightUseTwoMatActGeneral="82763" weightUseTwoRoadGeneral="69702">
		<fitness>43</fitness>
	</param>
	<param weightGoodNumbers="59971" weightPortThreeOne="82899" weightPortTwoOne="74702" weightMissingMaterial="30366" weightEdgeGeneral="63874" weightWood="12432" weightBrick="81070" weightGrain="57713" weightSheep="90904" weightStone="67497" weightRoadGeneral="5878" weightLongestRoad="95771" weightExtensionRoad="81426" weightSpaceForVillage="56869" weightThiefMoveBase="81551" weightThiefMoveOtherBuilding="58597" weightThiefMoveMyBuilding="98033" weightThiefMoveProb="66632" weightVillageGeneral="32383" weightVillageGoodNumbers="6104" weightVillagePortThreeOne="94092" weightVillagePortTwoOne="50703" weightTownGeneral="6233" weightTownGoodNumbers="93677" weightBuyActionCardGeneral="66470" weightUseActionCardGeneral="70168" weightUseMatFromPlGeneral="52656" weightUseTwoMatRoadGeneral="70324" weightUseTwoMatVillageGeneral="32560" weightUseTwoMatTownGeneral="36412" weightUseTwoMatActGeneral="59572" weightUseTwoRoadGeneral="32030">
		<fitness>50</fitness>
	</param>
	<param weightGoodNumbers="77596" weightPortThreeOne="81541" weightPortTwoOne="52732" weightMissingMaterial="26942" weightEdgeGeneral="84617" weightWood="38715" weightBrick="42473" weightGrain="57436" weightSheep="73344" weightStone="75852" weightRoadGeneral="22729" weightLongestRoad="92028" weightExtensionRoad="88212" weightSpaceForVillage="79576" weightThiefMoveBase="35658" weightThiefMoveOtherBuilding="43985" weightThiefMoveMyBuilding="16438" weightThiefMoveProb="32593" weightVillageGeneral="54719" weightVillageGoodNumbers="82066" weightVillagePortThreeOne="28536" weightVillagePortTwoOne="76658" weightTownGeneral="75611" weightTownGoodNumbers="9268" weightBuyActionCardGeneral="76665" weightUseActionCardGeneral="81026" weightUseMatFromPlGeneral="63896" weightUseTwoMatRoadGeneral="93707" weightUseTwoMatVillageGeneral="59776" weightUseTwoMatTownGeneral="10746" weightUseTwoMatActGeneral="25152" weightUseTwoRoadGeneral="54492">
		<fitness>95</fitness>
	</param>
	<param weightGoodNumbers="7924" weightPortThreeOne="73848" weightPortTwoOne="18175" weightMissingMaterial="99885" weightEdgeGeneral="4136" weightWood="54608" weightBrick="73981" weightGrain="59317" weightSheep="24159" weightStone="74948" weightRoadGeneral="32761" weightLongestRoad="18240" weightExtensionRoad="27973" weightSpaceForVillage="14206" weightThiefMoveBase="5465" weightThiefMoveOtherBuilding="86894" weightThiefMoveMyBuilding="34509" weightThiefMoveProb="8671" weightVillageGeneral="53885" weightVillageGoodNumbers="99968" weightVillagePortThreeOne="81694" weightVillagePortTwoOne="77507" weightTownGeneral="3493" weightTownGoodNumbers="937" weightBuyActionCardGeneral="5930" weightUseActionCardGeneral="43464" weightUseMatFromPlGeneral="50277" weightUseTwoMatRoadGeneral="3591" weightUseTwoMatVillageGeneral="74819" weightUseTwoMatTownGeneral="48766" weightUseTwoMatActGeneral="97660" weightUseTwoRoadGeneral="62597">
		<fitness>109</fitness>
	</param>
	<param weightGoodNumbers="50699" weightPortThreeOne="68237" weightPortTwoOne="84103" weightMissingMaterial="14363" weightEdgeGeneral="61401" weightWood="35773" weightBrick="39848" weightGrain="61830" weightSheep="58612" weightStone="95402" weightRoadGeneral="57906" weightLongestRoad="53589" weightExtensionRoad="43897" weightSpaceForVillage="57371" weightThiefMoveBase="81295" weightThiefMoveOtherBuilding="62458" weightThiefMoveMyBuilding="75560" weightThiefMoveProb="77002" weightVillageGeneral="59197" weightVillageGoodNumbers="51105" weightVillagePortThreeOne="56861" weightVillagePortTwoOne="25185" weightTownGeneral="72798" weightTownGoodNumbers="30418" weightBuyActionCardGeneral="70354" weightUseActionCardGeneral="17237" weightUseMatFromPlGeneral="93954" weightUseTwoMatRoadGeneral="60673" weightUseTwoMatVillageGeneral="4331" weightUseTwoMatTownGeneral="70389" weightUseTwoMatActGeneral="84498" weightUseTwoRoadGeneral="75393">
		<fitness>90</fitness>
	</param>
	<param weightGoodNumbers="77289" weightPortThreeOne="70164" weightPortTwoOne="67541" weightMissingMaterial="59736" weightEdgeGeneral="30104" weightWood="91103" weightBrick="25493" weightGrain="98737" weightSheep="68823" weightStone="92056" weightRoadGeneral="41355" weightLongestRoad="86293" weightExtensionRoad="19601" weightSpaceForVillage="49905" weightThiefMoveBase="57040" weightThiefMoveOtherBuilding="48560" weightThiefMoveMyBuilding="62170" weightThiefMoveProb="87820" weightVillageGeneral="28032" weightVillageGoodNumbers="97818" weightVillagePortThreeOne="89570" weightVillagePortTwoOne="46554" weightTownGeneral="5736" weightTownGoodNumbers="25514" weightBuyActionCardGeneral="95439" weightUseActionCardGeneral="53684" weightUseMatFromPlGeneral="44009" weightUseTwoMatRoadGeneral="44164" weightUseTwoMatVillageGeneral="41820" weightUseTwoMatTownGeneral="79176" weightUseTwoMatActGeneral="57499" weightUseTwoRoadGeneral="88224">
		<fitness>73</fitness>
	</param>
	<param weightGoodNumbers="10903" weightPortThreeOne="82513" weightPortTwoOne="76300" weightMissingMaterial="73734" weightEdgeGeneral="89830" weightWood="21558" weightBrick="32353" weightGrain="84458" weightSheep="51509" weightStone="60460" weightRoadGeneral="82283" weightLongestRoad="64806" weightExtensionRoad="83830" weightSpaceForVillage="86506" weightThiefMoveBase="10817" weightThiefMoveOtherBuilding="20448" weightThiefMoveMyBuilding="60197" weightThiefMoveProb="45393" weightVillageGeneral="98504" weightVillageGoodNumbers="16511" weightVillagePortThreeOne="42357" weightVillagePortTwoOne="86681" weightTownGeneral="85823" weightTownGoodNumbers="30734" weightBuyActionCardGeneral="64427" weightUseActionCardGeneral="42027" weightUseMatFromPlGeneral="64297" weightUseTwoMatRoadGeneral="76420" weightUseTwoMatVillageGeneral="47093" weightUseTwoMatTownGeneral="81329" weightUseTwoMatActGeneral="56917" weightUseTwoRoadGeneral="89648">
		<fitness>72</fitness>
	</param>
	<param weightGoodNumbers="34556" weightPortThreeOne="53132" weightPortTwoOne="75389" weightMissingMaterial="37088" weightEdgeGeneral="73605" weightWood="83307" weightBrick="58731" weightGrain="40611" weightSheep="55466" weightStone="43574" weightRoadGeneral="46308" weightLongestRoad="29109" weightExtensionRoad="64272" weightSpaceForVillage="40931" weightThiefMoveBase="41684" weightThiefMoveOtherBuilding="8933" weightThiefMoveMyBuilding="42867" weightThiefMoveProb="23560" weightVillageGeneral="83967" weightVillageGoodNumbers="96427" weightVillagePortThreeOne="80673" weightVillagePortTwoOne="40987" weightTownGeneral="45867" weightTownGoodNumbers="24222" weightBuyActionCardGeneral="96690" weightUseActionCardGeneral="45566" weightUseMatFromPlGeneral="9307" weightUseTwoMatRoadGeneral="47802" weightUseTwoMatVillageGeneral="57261" weightUseTwoMatTownGeneral="55934" weightUseTwoMatActGeneral="37364" weightUseTwoRoadGeneral="70180">
		<fitness>89</fitness>
	</param>
	<param weightGoodNumbers="3543" weightPortThreeOne="92636" weightPortTwoOne="30249" weightMissingMaterial="30698" weightEdgeGeneral="11117" weightWood="73729" weightBrick="46844" weightGrain="76891" weightSheep="86663" weightStone="57892" weightRoadGeneral="61046" weightLongestRoad="98783" weightExtensionRoad="40372" weightSpaceForVillage="56713" weightThiefMoveBase="66462" weightThiefMoveOtherBuilding="23496" weightThiefMoveMyBuilding="343" weightThiefMoveProb="55364" weightVillageGeneral="33552" weightVillageGoodNumbers="23532" weightVillagePortThreeOne="97362" weightVillagePortTwoOne="60491" weightTownGeneral="8974" weightTownGoodNumbers="93569" weightBuyActionCardGeneral="7264" weightUseActionCardGeneral="51167" weightUseMatFromPlGeneral="40398" weightUseTwoMatRoadGeneral="28039" weightUseTwoMatVillageGeneral="73999" weightUseTwoMatTownGeneral="10928" weightUseTwoMatActGeneral="83351" weightUseTwoRoadGeneral="99533">
		<fitness>70</fitness>
	</param>
	<param weightGoodNumbers="6210" weightPortThreeOne="76129" weightPortTwoOne="25566" weightMissingMaterial="71637" weightEdgeGeneral="10681" weightWood="10985" weightBrick="97817" weightGrain="69139" weightSheep="76717" weightStone="7076" weightRoadGeneral="9763" weightLongestRoad="22780" weightExtensionRoad="79942" weightSpaceForVillage="47084" weightThiefMoveBase="83851" weightThiefMoveOtherBuilding="39976" weightThiefMoveMyBuilding="79104" weightThiefMoveProb="85811" weightVillageGeneral="47459" weightVillageGoodNumbers="1896" weightVillagePortThreeOne="22381" weightVillagePortTwoOne="13832" weightTownGeneral="72818" weightTownGoodNumbers="43053" weightBuyActionCardGeneral="83661" weightUseActionCardGeneral="36680" weightUseMatFromPlGeneral="23434" weightUseTwoMatRoadGeneral="59951" weightUseTwoMatVillageGeneral="33330" weightUseTwoMatTownGeneral="18804" weightUseTwoMatActGeneral="2891" weightUseTwoRoadGeneral="75735">
		<fitness>37</fitness>
	</param>
</population>
